{
  "name": "Nuvla",
  "revision": "2017-05-10",
  "vendor_verified": "2015-10-13",
  "url": "https://nuv.la",
  "status": "production",
  "status_since": "2012-01-01",
  "type": "IaaS-centric",
  "hosting": {
    "public": true,
    "private": true
  },
  "pricings": [
    {
      "model": "metered",
      "period": "monthly"
    },
    {
      "model": "free",
      "period": ""
    }
  ],
  "scaling": {
    "horizontal": true,
    "vertical": true,
    "auto": false
  },
  "runtimes": [
    {
      "language": "python",
      "versions": [
        "*.*"
      ]
    },
    {
      "language": "ruby",
      "versions": [
        "*.*"
      ]
    }
  ],
  "middlewares": [],
  "frameworks": [],
  "services": {
    "native": [
      {
        "name": "SlipStream Engine",
        "description": "The Nuvla platform is powered by SlipStream.",
        "type": "deployment",
        "versions": [
          "2.17"
        ]
      },
      {
        "name": "Metering",
        "description": "Control the resources usage across all used clouds.",
        "type": "profiling",
        "versions": [
          "*.*"
        ]
      },
      {
        "name": "Events",
        "description": "Unified overview of all events related to the account and its deployments.",
        "type": "profiling",
        "versions": [
          "*.*"
        ]
      },
      {
        "name": "Usage",
        "description": "Aggregated and consolidated usage records.",
        "type": "management",
        "versions": [
          "*.*"
        ]
      },
      {
        "name": "Quotas",
        "description": "Per cloud quota enforcement.",
        "type": "management",
        "versions": [
          "*.*"
        ]
      },
      {
        "name": "Multi-tier",
        "description": "Group and account ACLs for all modules",
        "type": "management",
        "versions": [
          "*.*"
        ]
      },
      {
        "name": "MongoDB",
        "type": "database",
        "versions": [
          "3.0",
          "*.*"
        ]
      },
      {
        "name": "Couchbase",
        "type": "database",
        "versions": [
          "2.1.1",
          "*.*"
        ]
      }
    ],
    "addon": []
  },
  "extensible": true,
  "infrastructures": [
    {
      "continent": "AS",
      "country": "JP",
      "region": "Tokyo",
      "provider": "AWS"
    },
    {
      "continent": "AS",
      "country": "SG",
      "region": "Singapore",
      "provider": "AWS"
    },
    {
      "continent": "EU",
      "country": "IE",
      "region": "Dublin",
      "provider": "AWS"
    },
    {
      "continent": "EU",
      "country": "DE",
      "region": "Frankfurt",
      "provider": "AWS"
    },
    {
      "continent": "NA",
      "country": "US",
      "region": "N. Virginia",
      "provider": "AWS"
    },
    {
      "continent": "NA",
      "country": "US",
      "region": "N. California",
      "provider": "AWS"
    },
    {
      "continent": "NA",
      "country": "US",
      "region": "Oregon",
      "provider": "AWS"
    },
    {
      "continent": "OC",
      "country": "AU",
      "region": "Sydney",
      "provider": "AWS"
    },
    {
      "continent": "SA",
      "country": "BR",
      "region": "Sao Paulo",
      "provider": "AWS"
    },
    {
      "continent": "EU",
      "country": "CH",
      "region": "Geneva",
      "provider": "Exoscale"
    },
    {
      "continent": "EU",
      "country": "CZ",
      "region": "Prague",
      "provider": "Ultimum"
    }
  ]
}